{
  "alternate_locations": {
    "servers": [
      {
        "dir": "/0/items/fourhomelessmill0000leaf",
        "server": "dn710105.ca.archive.org"
      },
      {
        "dir": "/0/items/fourhomelessmill0000leaf",
        "server": "dn760109.eu.archive.org"
      }
    ],
    "workable": [
      {
        "dir": "/0/items/fourhomelessmill0000leaf",
        "server": "dn710105.ca.archive.org"
      },
      {
        "dir": "/0/items/fourhomelessmill0000leaf",
        "server": "dn760109.eu.archive.org"
      }
    ]
  },
  "created": 1781957360,
  "d1": "ia902809.us.archive.org",
  "d2": "ia802809.us.archive.org",
  "dir": "/16/items/fourhomelessmill0000leaf",
  "files": [
    {
      "crc32": "d6f75c07",
      "format": "Item Tile",
      "md5": "c51e042736469609ed971f7c0c7a7a66",
      "mtime": "1660033419",
      "name": "__ia_thumb.jpg",
      "rotation": "0",
      "sha1": "7836cf3de9954f60b13b75baffc6d29347e4ba8d",
      "size": "15285",
      "source": "original"
    },
    {
      "crc32": "b27a6ebd",
      "format": "EPUB",
      "hocr_epub_hocr_version": "1.1.62",
      "hocr_epub_module_version": "0.0.1",
      "md5": "e805f2573e72022c120beee4f2bc38d6",
      "mtime": "1753360206",
      "name": "fourhomelessmill0000leaf.epub",
      "original": "fourhomelessmill0000leaf_hocr.html",
      "private": "true",
      "sha1": "76b956af9de1939dad8b9ae406d4efa7aeaedd57",
      "size": "1135058",
      "source": "derivative"
    },
    {
      "crc32": "60e31cbe",
      "format": "LCP Encrypted PDF",
      "md5": "fd1b216dea6297f9f745a00f37d75dd7",
      "mtime": "1753360180",
      "name": "fourhomelessmill0000leaf.lcpdf",
      "original": "fourhomelessmill0000leaf.pdf",
      "sha1": "c2be746b045c63e65c496938ac359fe80967b72c",
      "size": "16253060",
      "source": "derivative"
    },
    {
      "crc32": "a3c12081",
      "format": "Text PDF",
      "md5": "f5d352719e79a4447353ffc188630595",
      "mtime": "1722548198",
      "name": "fourhomelessmill0000leaf.pdf",
      "original": "fourhomelessmill0000leaf_page_numbers.json",
      "private": "true",
      "sha1": "961f75d44beb8c9af6acc296afc59220b7e6d5cb",
      "size": "15956046",
      "source": "derivative"
    },
    {
      "crc32": "5757d6be",
      "format": "chOCR",
      "md5": "f991b709aaffb47c11bf11fa56c4a358",
      "mtime": "1622187446",
      "name": "fourhomelessmill0000leaf_chocr.html.gz",
      "ocr": "tesseract 5.0.0-alpha-20201231-10-g1236",
      "ocr_detected_lang": "en",
      "ocr_detected_lang_conf": "1.0000",
      "ocr_detected_script": "Latin",
      "ocr_detected_script_conf": "0.9262",
      "ocr_module_version": "0.0.13",
      "ocr_parameters": "-l eng",
      "original": "fourhomelessmill0000leaf_jp2.zip",
      "private": "true",
      "sha1": "9caa0281d07c5245e3cb5d3cede3f466fc966d17",
      "size": "7662801",
      "source": "derivative"
    },
    {
      "cloth_cover_detection_module_version": "1.2",
      "crc32": "6a82b809",
      "format": "Cloth Cover Detection Log",
      "md5": "9bf62c6a5058e4b1d3ccfd9731af8bbc",
      "mtime": "1670031943",
      "name": "fourhomelessmill0000leaf_cloth_detection.log",
      "original": "fourhomelessmill0000leaf_scandata.xml",
      "private": "true",
      "sha1": "4a7ef7122610ce791cc2d42cfc5dd207c281a248",
      "size": "789",
      "source": "derivative"
    },
    {
      "crc32": "fa3f2438",
      "format": "Dublin Core",
      "md5": "a46999930bf5b580049ecc158068cd1b",
      "mtime": "1666910730",
      "name": "fourhomelessmill0000leaf_dc.xml",
      "sha1": "d7a620f185e7dd65223cb1968629f294628c08b3",
      "size": "4265",
      "source": "original"
    },
    {
      "crc32": "87bad749",
      "format": "DjVuTXT",
      "md5": "9608dafe1013fa767cc03be2ae5edbce",
      "mtime": "1622191806",
      "name": "fourhomelessmill0000leaf_djvu.txt",
      "original": "fourhomelessmill0000leaf_djvu.xml",
      "private": "true",
      "sha1": "cbecd48edd5967c04dfe3ca86bad99ff199a3e00",
      "size": "563995",
      "source": "derivative"
    },
    {
      "crc32": "b586b043",
      "format": "Djvu XML",
      "md5": "245559fe362e43c53eab18f20d11e5a0",
      "mtime": "1622191729",
      "name": "fourhomelessmill0000leaf_djvu.xml",
      "original": "fourhomelessmill0000leaf_hocr.html",
      "private": "true",
      "sha1": "290b70c969a45837678868b137755cd739c60363",
      "size": "7676609",
      "source": "derivative"
    },
    {
      "crc32": "c77280c9",
      "format": "ACS Encrypted PDF",
      "md5": "c9356f0cdf66979c4c0834b2c9d031fa",
      "mtime": "1722548840",
      "name": "fourhomelessmill0000leaf_encrypted.pdf",
      "original": "fourhomelessmill0000leaf.pdf",
      "sha1": "c7da511512bbd06bf98170155a39ec84db24e728",
      "size": "15876705",
      "source": "derivative"
    },
    {
      "crc32": "58aa7a0f",
      "format": "JSON",
      "md5": "baa25d628565162c065fcc2323410eee",
      "mtime": "1622174957",
      "name": "fourhomelessmill0000leaf_events.json",
      "private": "true",
      "sha1": "7c0823a52200584d82a914a6d971d2e2ed63dff8",
      "size": "54",
      "source": "original"
    },
    {
      "format": "Metadata",
      "md5": "47dd0a8f65636e945c7e971fb436cbac",
      "name": "fourhomelessmill0000leaf_files.xml",
      "source": "original",
      "summation": "md5"
    },
    {
      "crc32": "7c01150f",
      "format": "hOCR",
      "hocr_char_to_word_hocr_version": "1.1.2",
      "hocr_char_to_word_module_version": "1.0.0",
      "md5": "692edb44ce76cf13edfe4a58d73f06ab",
      "mtime": "1622191669",
      "name": "fourhomelessmill0000leaf_hocr.html",
      "ocr_detected_lang": "en",
      "ocr_detected_lang_conf": "1.0000",
      "ocr_detected_script": "Latin",
      "ocr_detected_script_conf": "0.9262",
      "ocr_module_version": "0.0.13",
      "ocr_parameters": "-l eng",
      "original": "fourhomelessmill0000leaf_chocr.html.gz",
      "private": "true",
      "sha1": "913d710534c2d3736972d8dfa074f0a9b891b261",
      "size": "14103325",
      "source": "derivative"
    },
    {
      "crc32": "b71db7d7",
      "format": "OCR Page Index",
      "hocr_pageindex_hocr_version": "1.1.0",
      "hocr_pageindex_module_version": "1.0.0",
      "md5": "50ad3220bb4c5702495f895d2e3af468",
      "mtime": "1622191764",
      "name": "fourhomelessmill0000leaf_hocr_pageindex.json.gz",
      "original": "fourhomelessmill0000leaf_hocr.html",
      "private": "true",
      "sha1": "42af247239294b213cdec36bad9ba399a956cb31",
      "size": "3766",
      "source": "derivative"
    },
    {
      "crc32": "59728ac8",
      "format": "OCR Search Text",
      "hocr_fts_text_hocr_version": "1.1.0",
      "hocr_fts_text_module_version": "1.1.0",
      "md5": "76c7c1be16fb84a2f58df38e2f21288f",
      "mtime": "1622191792",
      "name": "fourhomelessmill0000leaf_hocr_searchtext.txt.gz",
      "original": "fourhomelessmill0000leaf_hocr.html",
      "private": "true",
      "sha1": "f27c3d2ce0ffc70c4365bc21da0c8df40f66a16e",
      "size": "221548",
      "source": "derivative",
      "word_conf_0_10": "362",
      "word_conf_11_20": "201",
      "word_conf_21_30": "262",
      "word_conf_31_40": "235",
      "word_conf_41_50": "154",
      "word_conf_51_60": "138",
      "word_conf_61_70": "149",
      "word_conf_71_80": "173",
      "word_conf_81_90": "1105",
      "word_conf_91_100": "96562"
    },
    {
      "crc32": "462a2769",
      "filecount": "318",
      "format": "Single Page Processed JP2 ZIP",
      "md5": "611c901fb9a44d2cb72cbd2f4584e18f",
      "mtime": "1622184220",
      "name": "fourhomelessmill0000leaf_jp2.zip",
      "original": "fourhomelessmill0000leaf_orig_jp2.tar",
      "private": "true",
      "sha1": "59e1fc819f23b994314b150c1cdef3aaabaca589",
      "size": "143265778",
      "source": "derivative"
    },
    {
      "crc32": "6e5d4d98",
      "format": "LCP Encrypted EPUB",
      "md5": "2be3f6268434ff4857f9db70c78a1d85",
      "mtime": "1753360237",
      "name": "fourhomelessmill0000leaf_lcp.epub",
      "original": "fourhomelessmill0000leaf.epub",
      "sha1": "e0076b9afad2b93e24f28b4ecc03f4480392974b",
      "size": "1151749",
      "source": "derivative"
    },
    {
      "crc32": "f79b9978",
      "format": "MARC",
      "md5": "294488cade406f75808bacca56abe8cf",
      "mtime": "1622101633",
      "name": "fourhomelessmill0000leaf_marc.xml",
      "sha1": "6b6480f0c48fa2ad6fb93957bbf129e69c4cbb60",
      "size": "8286",
      "source": "original"
    },
    {
      "crc32": "440fbd68",
      "format": "MARC Binary",
      "md5": "6ace7211f69e1819a889ad5eafccf2f9",
      "mtime": "1622101630",
      "name": "fourhomelessmill0000leaf_meta.mrc",
      "sha1": "28910280b8aeca8bf80ab040d271a55182a21a8e",
      "size": "4527",
      "source": "original"
    },
    {
      "crc32": "3b1c2019",
      "format": "Metadata",
      "md5": "e4859f21e0b25c7f4815463668cc4108",
      "mtime": "1622175032",
      "name": "fourhomelessmill0000leaf_meta.sqlite",
      "sha1": "837a6aad42fc1be21bccdb9ec2e0024aab426b10",
      "size": "49152",
      "source": "original"
    },
    {
      "crc32": "e142b2c6",
      "format": "Metadata",
      "md5": "aa62f1d2e4a89e8f325c3ebb6ca65020",
      "mtime": "1773646835",
      "name": "fourhomelessmill0000leaf_meta.xml",
      "sha1": "3381f2e78ce35c65c41e2b461b035afd04c866d7",
      "size": "6269",
      "source": "original"
    },
    {
      "crc32": "afbf6412",
      "filecount": "318",
      "format": "Single Page Original JP2 Tar",
      "md5": "14adec50f06b8af802ec48b603ac52a5",
      "mtime": "1622175031",
      "name": "fourhomelessmill0000leaf_orig_jp2.tar",
      "private": "true",
      "sha1": "2ace1ce54c46eef2980a859774b94734c2918590",
      "size": "468817920",
      "source": "original"
    },
    {
      "crc32": "0fae3a3b",
      "format": "Page Numbers JSON",
      "hocr_pagenumber_confidence": "99",
      "hocr_pagenumber_hocr_version": "1.1.54",
      "hocr_pagenumber_module_version": "1.0.5",
      "md5": "4c912cae6ec5afe8df56c750714b69c6",
      "mtime": "1722548197",
      "name": "fourhomelessmill0000leaf_page_numbers.json",
      "original": "fourhomelessmill0000leaf_hocr.html",
      "private": "true",
      "sha1": "c2c239795542c09f8f3a605a99e426793da2a840",
      "size": "53025",
      "source": "derivative"
    },
    {
      "crc32": "e4f82603",
      "format": "Scandata",
      "md5": "79b6ff34b730008891e4f7a01f9028db",
      "mtime": "1670031943",
      "name": "fourhomelessmill0000leaf_scandata.xml",
      "sha1": "e64d0172e833d82eb3c7391738feb0a2e88524c0",
      "size": "345998",
      "source": "original"
    },
    {
      "crc32": "6c93e4f0",
      "format": "PNG",
      "md5": "7ff57cc4cfa52a7b39a861dc648af936",
      "mtime": "1622090965",
      "name": "fourhomelessmill0000leaf_slip.png",
      "private": "true",
      "sha1": "a9fe1e155899591d51ea87b5092d5b2e8781c0a3",
      "size": "39178",
      "source": "original"
    },
    {
      "crc32": "062e4737",
      "format": "JPEG Thumb",
      "md5": "91fc1aefa36e399592c3b0a6eadae560",
      "mtime": "1622175073",
      "name": "fourhomelessmill0000leaf_slip_thumb.jpg",
      "original": "fourhomelessmill0000leaf_slip.png",
      "private": "true",
      "sha1": "75b23fde3d607b9211c98964ff9f9b9d583081a6",
      "size": "8505",
      "source": "derivative"
    },
    {
      "crc32": "65d14dac",
      "format": "Title Page Detection Log",
      "md5": "c42c6e14e1b2f02439ee946fa27f8cab",
      "mtime": "1670031577",
      "name": "fourhomelessmill0000leaf_title_detection.log",
      "original": "fourhomelessmill0000leaf_djvu.xml",
      "private": "true",
      "sha1": "871736592da89d3cf7cd7ee3a3db2aaee57a91ff",
      "size": "573",
      "source": "derivative"
    },
    {
      "crc32": "df2e7833",
      "format": "Log",
      "md5": "cd576348c0f75f4e76597eb65253a6c1",
      "mtime": "1622101639",
      "name": "logs/fourhomelessmill0000leaf_iabdash_2021-05-2715:47:16.log",
      "private": "true",
      "sha1": "f9df9438b20c2d9d79e0e6b8f123356b9f596df1",
      "size": "673",
      "source": "original"
    },
    {
      "crc32": "8752b6f6",
      "format": "Log",
      "md5": "ac680929f8928f47bc626bb7b6cd0385",
      "mtime": "1622101646",
      "name": "logs/fourhomelessmill0000leaf_scanning_2021-05-2715:47:22.log",
      "private": "true",
      "sha1": "6a9fd3c935243557a1ea2c615c95d23bba101a55",
      "size": "959305",
      "source": "original"
    },
    {
      "crc32": "79c4bede",
      "format": "Log",
      "md5": "343a9696468ec91219e53cc2131b5b1b",
      "mtime": "1622101642",
      "name": "logs/fourhomelessmill0000leaf_status_history_2021-05-2715:47:19.log",
      "private": "true",
      "sha1": "3895d5eea558004a69bf426e96040995e9593a55",
      "size": "406",
      "source": "original"
    }
  ],
  "files_count": 30,
  "item_last_updated": 1773646835,
  "item_size": 694184650,
  "metadata": {
    "access-restricted-item": "true",
    "addeddate": "2021-06-01 17:50:51",
    "boxid": "IA40125207",
    "camera": "USB PTP Class Camera",
    "collection": [
      "internetarchivebooks",
      "inlibrary",
      "printdisabled"
    ],
    "collection_set": "printdisabled",
    "contributor": "Internet Archive",
    "creator": "Leaf, Rik, author",
    "date": "2015",
    "description": [
      "1 online resource",
      "In the throes of a global recession, Rik and Zara Leaf sold their house and spent a year traveling around the world with their son Zion, and daughter Riel, investing their life savings in a laugh out loud adventure of a lifetime. The family filmed horror movies in Canada, ate mafia-made pizza in Germany, got caught sneaking onto a Hollywood set in Hawaii, survived a feral dog attack in Malaysia and dorsal fins emerging from the surf as they swam off the Australian coast. The thought of abandoning conventional wisdom and getting away with it was too exciting to pass up. Of course, the decision to really 'go for it' involved lots of anxious 'what ifs' and 'are we out of our frigging minds?' Throughout the year they produced a videos series called, \"Where in the World are Zion & Riel?\" QR codes linked to these videos are included in the book, creating an amazing interactive reading experience",
      "Vendor-supplied metadata",
      "Cover; Title Page; Contents; Preface; Canada; A Whirlwind of EpicNose-Plowing Proportions; The Sacrilegious Spirit In The Embryonic Soup; The Most Realistic People On the Planet; Holy S#*! Babe! That's Messed Up; Reduced to a Puddle of Blubbering Tears; God, Guns & Glory; Anti-Social Middle Aged Basement Dwellers; Candy-Coated Duvet Covers and Kool-Aid Waterslides; Sounds from Deep Within an Esophagus; Cujo-Meets-The-Blair-Witch; HaWaii; The Calm Behind a Medicated Exterior; Man-Eating Mandibles and Surly Dispositions; Über Conservative Christians, Mormons & Mermaids; malaysia",
      "Rock Star Swagger With Cock-On-The-Block PizzazzThe Host of Heaven Laughing Their Asses Off; A Shifty Musician With aWonky Astigmatism; The Demonic Roar of Genetically Modified Vocal Chords; ausTralia; Horror Porn For Overactive Imaginations; Barrel-Assing Into the Pit of Hell; The Only Thing a Loving Father Could Do; Horror Picture People; A 12-Foot Tall Naked Hairy Man; A Metallic Gunshot As Stars Explode In My Eyes; Swarthy Swashbucklers and Nautical Hazing Rituals; neW zealand; Defense of Persecuted Penguin Retinas; It Might Not Be Art But It Sure is Creative",
      "Last Night I Paid 50.00 For SexGiggles, Guffaws and FruityTears of Mirth; An Agonizing Belly Crawl of Pain and Shame; A Psychosomatic Figment of the Collective Imagination; iTaly/franCe; A Pint-Sized Grim Reaper & a Weird Ass Creepfest; A Glorious Array of Magnificent Fermentation; Tour De Franco; Italian Stallions at a Caffeine Rodeo; In the Name of God and the Holy Church; The Bee's Knees is Now the Cat's Ass; denmark/sWeden; Embryonic Building Blocks & Lego Genetics; The Scandinavian Centipede is Closer Than It Appears; The Rampage of Tintin the Terrible; sWiTzerland/germany",
      "One Man's Coffee Break is Another Woman's VaginaA Callous Cad & a Brood of Dirty-Faced Street Urchins; england; Carpet Bombing Brighton's Downtown; The Richest People In the World; Teeth, Talons & Cuddly Balls of Fluff; Dark Clouds & Silver Linings; Canada; Digging Deep, Down the Homeless Stretch; Copyright"
    ],
    "external-identifier": [
      "urn:acs6:fourhomelessmill0000leaf:pdf:0b5a2f43-d7ff-4aa1-a2f0-2963f673119c",
      "urn:oclc:record:969027762",
      "urn:lcp:fourhomelessmill0000leaf:lcpdf:36907f8f-2a99-4b2f-a3d9-1a001b5e11ef",
      "urn:lcp:fourhomelessmill0000leaf:epub:57275026-8cb5-42a1-b471-4d613ee6c7ff"
    ],
    "foldoutcount": "0",
    "identifier": "fourhomelessmill0000leaf",
    "identifier-access": "http://archive.org/details/fourhomelessmill0000leaf",
    "identifier-ark": "ark:/13960/t1tg12k05",
    "imagecount": "318",
    "invoice": "1652",
    "isbn": [
      "9781927559918",
      "192755991X",
      "9781927559901"
    ],
    "language": "eng",
    "mediatype": "texts",
    "oclc-id": [
      "969027762",
      "968017242",
      "1048790441",
      "1048934856"
    ],
    "ocr": "tesseract 5.0.0-alpha-20201231-10-g1236",
    "ocr_detected_lang": "en",
    "ocr_detected_lang_conf": "1.0000",
    "ocr_detected_script": "Latin",
    "ocr_detected_script_conf": "0.9262",
    "ocr_module_version": "0.0.13",
    "ocr_parameters": "-l eng",
    "old_pallet": "IA-NS-0000544",
    "openlibrary_edition": "OL28934819M",
    "openlibrary_work": "OL21361139W",
    "operator": "associate-darius-subang@archive.org",
    "page_number_confidence": "99",
    "page_number_module_version": "1.0.5",
    "pdf_module_version": "0.0.14",
    "ppi": "360",
    "publicdate": "2021-05-27 04:49:37",
    "publisher": "Promontory Press",
    "rcs_key": "24143",
    "repub_state": "19",
    "republisher_date": "20210528120907",
    "republisher_operator": "associate-jed-ballener@archive.org",
    "republisher_time": "295",
    "scandate": "20210527083900",
    "scanfee": "0;1.00;200",
    "scanner": "station48.cebu.archive.org",
    "scanningcenter": "cebu",
    "scribe3_search_catalog": "isbn",
    "scribe3_search_id": "9781927559901",
    "sponsordate": "20210531",
    "title": "Four Homeless Millionaires",
    "tts_version": "4.5-initial-63-g7e8faad7",
    "uploader": "station48.cebu@archive.org"
  },
  "server": "ia802809.us.archive.org",
  "uniq": 2056692830,
  "workable_servers": [
    "ia802809.us.archive.org",
    "ia902809.us.archive.org"
  ]
}