{
  "updated_at": "2026-06-23T00:38:18.808217Z",
  "stage_dir": "multiple post-launch staged route directories",
  "starting_public_records": 3752,
  "ending_public_records": 3809,
  "net_new_public_records": 57,
  "starting_map_flags": 1200,
  "ending_map_flags": 1206,
  "net_new_map_flags": 6,
  "current_public_records": 3809,
  "gap_to_minimum_3500": 0,
  "gap_to_preferred_3800": 0,
  "soft_ceiling_remaining": 191,
  "current_map_flags": 1206,
  "gap_to_map_1200": 0,
  "current_map_ratio": 0.3166,
  "records_added_since_checkpoint": 7,
  "map_flags_added_since_checkpoint": 0,
  "records_per_new_map_flag": null,
  "active_collection_mode": "complete",
  "candidates_processed": 118,
  "postlaunch_records_reviewed_or_suppressed": 118,
  "suppressed_scope_qa_record_ids": [
    4158,
    4159,
    4175,
    4176,
    4177,
    4178,
    4179,
    4182,
    4184,
    4187,
    4196,
    4199,
    4200,
    4201,
    4202,
    4203,
    4204,
    4205,
    4211
  ],
  "by_source_organisation": {
    "Internet Archive": 27,
    "Australian Broadcasting Corporation": 21,
    "Internet Sacred Text Archive": 8
  },
  "by_source_family": {
    "repository_institutional_full_text": 27,
    "institutional_public_media_records": 21,
    "structured_public_domain_books": 8
  },
  "by_jurisdiction": {
    "NT": 26,
    "unmapped/broad": 20,
    "WA": 4,
    "NSW": 3,
    "TAS": 2,
    "SA": 1
  },
  "by_narrative_type": {
    "repository_full_text": 27,
    "institutional_media_page": 20,
    "public_domain_transcribed_book": 8,
    "institutional_education_page": 1
  },
  "route_totals": {
    "sprint_postlaunch_abc_wa_modern_places_63": {
      "processed": 1,
      "accepted": 0,
      "context": 0,
      "duplicates": 0,
      "rejected": 1,
      "errors": 0,
      "map_candidates": 0
    },
    "sprint_postlaunch_abc_tas_modern_places_66": {
      "processed": 3,
      "accepted": 0,
      "context": 0,
      "duplicates": 2,
      "rejected": 1,
      "errors": 0,
      "map_candidates": 0
    },
    "sprint_postlaunch_abc_underrep_modern_broad_67": {
      "processed": 1,
      "accepted": 0,
      "context": 0,
      "duplicates": 1,
      "rejected": 0,
      "errors": 0,
      "map_candidates": 0
    },
    "sprint_postlaunch_abc_alison_oborn_adelaide_gaol_70": {
      "processed": 1,
      "accepted": 1,
      "context": 0,
      "duplicates": 0,
      "rejected": 0,
      "errors": 0,
      "map_candidates": 0
    },
    "sprint_postlaunch_abc_sylvania_friendly_ghost_69": {
      "processed": 1,
      "accepted": 1,
      "context": 0,
      "duplicates": 0,
      "rejected": 0,
      "errors": 0,
      "map_candidates": 0
    },
    "sprint_postlaunch_abc_arthur_marrin_hairy_man_73": {
      "processed": 1,
      "accepted": 1,
      "context": 0,
      "duplicates": 0,
      "rejected": 0,
      "errors": 0,
      "map_candidates": 0
    },
    "sprint_postlaunch_abc_urban_legends_yowies_74": {
      "processed": 1,
      "accepted": 1,
      "context": 0,
      "duplicates": 0,
      "rejected": 0,
      "errors": 0,
      "map_candidates": 0
    },
    "sprint_abc_willow_court_documentary_context_38": {
      "processed": 1,
      "accepted": 0,
      "context": 0,
      "duplicates": 0,
      "rejected": 1,
      "errors": 0,
      "map_candidates": 0
    },
    "sprint_postlaunch_abc_ngabaya_spirit_people_75": {
      "processed": 1,
      "accepted": 1,
      "context": 0,
      "duplicates": 0,
      "rejected": 0,
      "errors": 0,
      "map_candidates": 0
    },
    "sprint_postlaunch_abc_australian_ghost_stories_71": {
      "processed": 1,
      "accepted": 1,
      "context": 0,
      "duplicates": 0,
      "rejected": 0,
      "errors": 0,
      "map_candidates": 0
    },
    "sprint_postlaunch_abc_yahoo_creek_bigfoot_72": {
      "processed": 1,
      "accepted": 1,
      "context": 0,
      "duplicates": 0,
      "rejected": 0,
      "errors": 0,
      "map_candidates": 0
    },
    "sprint_postlaunch_abc_shadow_trackers_indigenous_ghosts_76": {
      "processed": 1,
      "accepted": 1,
      "context": 0,
      "duplicates": 0,
      "rejected": 0,
      "errors": 0,
      "map_candidates": 0
    },
    "sprint_postlaunch_abc_indigenous_ghost_stories_darkside_77": {
      "processed": 1,
      "accepted": 1,
      "context": 0,
      "duplicates": 0,
      "rejected": 0,
      "errors": 0,
      "map_candidates": 0
    },
    "sprint_postlaunch_abc_port_arthur_ghost_stories_80": {
      "processed": 1,
      "accepted": 1,
      "context": 0,
      "duplicates": 0,
      "rejected": 0,
      "errors": 0,
      "map_candidates": 0
    },
    "sprint_postlaunch_abc_monte_cristo_lawrence_ryan_82": {
      "processed": 1,
      "accepted": 1,
      "context": 0,
      "duplicates": 0,
      "rejected": 0,
      "errors": 0,
      "map_candidates": 0
    },
    "sprint_postlaunch_abc_sirius_resident_ghost_81": {
      "processed": 1,
      "accepted": 1,
      "context": 0,
      "duplicates": 0,
      "rejected": 0,
      "errors": 0,
      "map_candidates": 0
    },
    "sprint_postlaunch_abc_tamar_valley_tales_ghost_blog_79": {
      "processed": 1,
      "accepted": 1,
      "context": 0,
      "duplicates": 0,
      "rejected": 0,
      "errors": 0,
      "map_candidates": 0
    },
    "sprint_postlaunch_abc_wa_graham_seal_ghost_stories_78": {
      "processed": 1,
      "accepted": 1,
      "context": 0,
      "duplicates": 0,
      "rejected": 0,
      "errors": 0,
      "map_candidates": 0
    },
    "sprint_internet_archive_booandik_sa_exact_text": {
      "processed": 2,
      "accepted": 2,
      "context": 0,
      "duplicates": 0,
      "rejected": 0,
      "errors": 0,
      "map_candidates": 0
    },
    "sprint_internet_archive_native_tribes_nt_rescan_02": {
      "processed": 24,
      "accepted": 24,
      "context": 0,
      "duplicates": 0,
      "rejected": 0,
      "errors": 0,
      "map_candidates": 0
    },
    "sprint_sacred_texts_nw_wa_customs_traditions_exact_text": {
      "processed": 4,
      "accepted": 3,
      "context": 0,
      "duplicates": 1,
      "rejected": 0,
      "errors": 0,
      "map_candidates": 0
    },
    "sprint_internet_archive_roth_tasmania_rescan_02": {
      "processed": 5,
      "accepted": 5,
      "context": 0,
      "duplicates": 0,
      "rejected": 0,
      "errors": 0,
      "map_candidates": 0
    },
    "sprint_postlaunch_abc_burnie_arts_centre_ghost_83": {
      "processed": 1,
      "accepted": 1,
      "context": 0,
      "duplicates": 0,
      "rejected": 0,
      "errors": 0,
      "map_candidates": 0
    },
    "sprint_postlaunch_abc_djimubarn_mimih_context_84": {
      "processed": 1,
      "accepted": 1,
      "context": 0,
      "duplicates": 0,
      "rejected": 0,
      "errors": 0,
      "map_candidates": 0
    },
    "sprint_ista_northern_australia_exact_texts": {
      "processed": 8,
      "accepted": 2,
      "context": 0,
      "duplicates": 6,
      "rejected": 0,
      "errors": 0,
      "map_candidates": 0
    },
    "sprint_ista_central_australia_exact_texts": {
      "processed": 15,
      "accepted": 6,
      "context": 0,
      "duplicates": 9,
      "rejected": 0,
      "errors": 0,
      "map_candidates": 0
    },
    "sprint_internet_archive_northern_tribes_central_australia_rescan_02": {
      "processed": 8,
      "accepted": 8,
      "context": 0,
      "duplicates": 0,
      "rejected": 0,
      "errors": 0,
      "map_candidates": 0
    },
    "sprint_internet_archive_moore_wa_vocabulary_exact_text": {
      "processed": 5,
      "accepted": 4,
      "context": 0,
      "duplicates": 1,
      "rejected": 0,
      "errors": 0,
      "map_candidates": 0
    },
    "sprint_project_gutenberg_boldrewood_last_chance_exact_text": {
      "processed": 7,
      "accepted": 0,
      "context": 0,
      "duplicates": 6,
      "rejected": 1,
      "errors": 0,
      "map_candidates": 0
    },
    "sprint_project_gutenberg_lawson_over_the_sliprails_exact_text": {
      "processed": 4,
      "accepted": 0,
      "context": 0,
      "duplicates": 4,
      "rejected": 0,
      "errors": 0,
      "map_candidates": 0
    },
    "sprint_project_gutenberg_steele_rudd_on_our_selection_exact_text": {
      "processed": 9,
      "accepted": 0,
      "context": 0,
      "duplicates": 8,
      "rejected": 1,
      "errors": 0,
      "map_candidates": 0
    },
    "sprint_postlaunch_abc_cleverman_hairy_people_context_85": {
      "processed": 3,
      "accepted": 3,
      "context": 0,
      "duplicates": 0,
      "rejected": 0,
      "errors": 0,
      "map_candidates": 0
    },
    "sprint_postlaunch_abc_fanny_balbuk_spirit_places_87": {
      "processed": 1,
      "accepted": 1,
      "context": 0,
      "duplicates": 0,
      "rejected": 0,
      "errors": 0,
      "map_candidates": 0
    },
    "sprint_postlaunch_abc_jawoyn_mimi_spirit_people_86": {
      "processed": 1,
      "accepted": 1,
      "context": 0,
      "duplicates": 0,
      "rejected": 0,
      "errors": 0,
      "map_candidates": 0
    }
  },
  "productive_routes": [
    "sprint_postlaunch_abc_alison_oborn_adelaide_gaol_70",
    "sprint_postlaunch_abc_sylvania_friendly_ghost_69",
    "sprint_postlaunch_abc_arthur_marrin_hairy_man_73",
    "sprint_postlaunch_abc_urban_legends_yowies_74",
    "sprint_postlaunch_abc_ngabaya_spirit_people_75",
    "sprint_postlaunch_abc_australian_ghost_stories_71",
    "sprint_postlaunch_abc_yahoo_creek_bigfoot_72",
    "sprint_postlaunch_abc_shadow_trackers_indigenous_ghosts_76",
    "sprint_postlaunch_abc_indigenous_ghost_stories_darkside_77",
    "sprint_postlaunch_abc_port_arthur_ghost_stories_80",
    "sprint_postlaunch_abc_monte_cristo_lawrence_ryan_82",
    "sprint_postlaunch_abc_sirius_resident_ghost_81",
    "sprint_postlaunch_abc_tamar_valley_tales_ghost_blog_79",
    "sprint_postlaunch_abc_wa_graham_seal_ghost_stories_78",
    "sprint_internet_archive_booandik_sa_exact_text",
    "sprint_internet_archive_native_tribes_nt_rescan_02",
    "sprint_sacred_texts_nw_wa_customs_traditions_exact_text",
    "sprint_internet_archive_roth_tasmania_rescan_02",
    "sprint_postlaunch_abc_burnie_arts_centre_ghost_83",
    "sprint_postlaunch_abc_djimubarn_mimih_context_84",
    "sprint_ista_northern_australia_exact_texts",
    "sprint_ista_central_australia_exact_texts",
    "sprint_internet_archive_northern_tribes_central_australia_rescan_02",
    "sprint_internet_archive_moore_wa_vocabulary_exact_text",
    "sprint_postlaunch_abc_cleverman_hairy_people_context_85",
    "sprint_postlaunch_abc_fanny_balbuk_spirit_places_87",
    "sprint_postlaunch_abc_jawoyn_mimi_spirit_people_86"
  ],
  "exhausted_routes": [
    "sprint_postlaunch_abc_wa_modern_places_63",
    "sprint_postlaunch_abc_tas_modern_places_66",
    "sprint_postlaunch_abc_underrep_modern_broad_67",
    "sprint_abc_willow_court_documentary_context_38",
    "sprint_project_gutenberg_boldrewood_last_chance_exact_text",
    "sprint_project_gutenberg_lawson_over_the_sliprails_exact_text",
    "sprint_project_gutenberg_steele_rudd_on_our_selection_exact_text"
  ],
  "map_invariant": {
    "ok": true,
    "map_flags": 1206,
    "map_points": 1206,
    "mapped_record_count": 1206
  },
  "validation_ok": true,
  "build_run": false,
  "notes": [
    "Post-launch information capture continued after launch targets; frontend build intentionally not rerun for this data checkpoint.",
    "WA/NT/SA/TAS and 1970-present institutional media/context routes were prioritized where source evidence was available."
  ]
}
